dotkeep/__init__.py
dotkeep/cli.py
dotkeep/core.py
dotkeep/watcher.py
dotkeep-0.3.0.dist-info/licenses/LICENSE
dotkeep-0.3.0.dist-info/METADATA
dotkeep-0.3.0.dist-info/WHEEL
dotkeep-0.3.0.dist-info/entry_points.txt
dotkeep-0.3.0.dist-info/top_level.txt
dotkeep-0.3.0.dist-info/RECORD
