Metadata-Version: 2.4
Name: dotkeep
Version: 0.3.0
Summary: dotkeep is a minimal, Git-backed dotfiles manager for Linux
Author-email: Moustafa Salem <salemmoustafa442@gmail.com>
License: GPL-3.0-or-later
Project-URL: Homepage, https://github.com/tTrmc/dotkeep
Project-URL: Repository, https://github.com/tTrmc/dotkeep
Project-URL: Documentation, https://github.com/tTrmc/dotkeep#readme
Project-URL: Issues, https://github.com/tTrmc/dotkeep/issues
Project-URL: Changelog, https://github.com/tTrmc/dotkeep/releases
Keywords: dotfiles,git,configuration,linux,symlink,backup
Classifier: Development Status :: 4 - Beta
Classifier: Environment :: Console
Classifier: Intended Audience :: Developers
Classifier: Intended Audience :: End Users/Desktop
Classifier: Operating System :: POSIX :: Linux
Classifier: Programming Language :: Python :: 3
Classifier: Programming Language :: Python :: 3.8
Classifier: Programming Language :: Python :: 3.9
Classifier: Programming Language :: Python :: 3.10
Classifier: Programming Language :: Python :: 3.11
Classifier: Programming Language :: Python :: 3.12
Classifier: Programming Language :: Python :: 3.13
Classifier: Topic :: System :: Archiving :: Backup
Classifier: Topic :: System :: Systems Administration
Classifier: Topic :: Utilities
Requires-Python: >=3.8
License-File: LICENSE
Requires-Dist: typer
Requires-Dist: gitpython
Requires-Dist: watchdog
Provides-Extra: test
Requires-Dist: pytest>=6.0; extra == "test"
Requires-Dist: pytest-cov; extra == "test"
Provides-Extra: dev
Requires-Dist: pytest>=6.0; extra == "dev"
Requires-Dist: pytest-cov; extra == "dev"
Requires-Dist: black; extra == "dev"
Requires-Dist: isort; extra == "dev"
Requires-Dist: flake8; extra == "dev"
Requires-Dist: mypy; extra == "dev"
Dynamic: license-file
